LICENSE.txt
MANIFEST.in
README.rst
setup.py
assets_angular/__init__.py
assets_angular/assets.py
assets_angular/models.py
assets_angular.egg-info/PKG-INFO
assets_angular.egg-info/SOURCES.txt
assets_angular.egg-info/dependency_links.txt
assets_angular.egg-info/top_level.txt