Metadata-Version: 1.1
Name: assets-angular
Version: 0.1.0
Summary: Django_assets angular template filter.
Home-page: https://github.com/josesanch/assets_angular
Author: José Sánchez Moreno
Author-email: jose@o2w.es
License: MIT
Platform: All platforms
Classifier: Development Status :: 4 - Beta
Classifier: Intended Audience :: Developers
Classifier: License :: OSI Approved :: Python Software Foundation License
Classifier: Operating System :: MacOS :: MacOS X
Classifier: Operating System :: Microsoft :: Windows
Classifier: Operating System :: POSIX
Classifier: Programming Language :: Python
